Metadata-Version: 1.0
Name: hutil
Version: 0.1
Summary: Helper utilities
Home-page: http://github.com/hunan-rostomyan/hutil
Author: Hunan Rostomyan
Author-email: hunan131@gmail.com
License: BSD 3-Clause
Platform: UNKNOWN
